MANIFEST.in
README.md
setup.cfg
setup.py
cz_nia/__init__.py
cz_nia/constants.py
cz_nia/exceptions.py
cz_nia/functions.py
cz_nia/message.py
cz_nia/py.typed
cz_nia/settings.py
cz_nia.egg-info/PKG-INFO
cz_nia.egg-info/SOURCES.txt
cz_nia.egg-info/dependency_links.txt
cz_nia.egg-info/not-zip-safe
cz_nia.egg-info/requires.txt
cz_nia.egg-info/top_level.txt
cz_nia/__pycache__/__init__.cpython-38.pyc
cz_nia/schema/EvidenceVIPZapisRequest.xsd
cz_nia/schema/EvidenceZmenaRequest.xsd
cz_nia/schema/NotifikaceIdpRequest.xsd
cz_nia/schema/ZtotozneniRequest.xsd
cz_nia/schema/__init__.py
cz_nia/tests/__init__.py
cz_nia/tests/assertion.xml
cz_nia/tests/certificate.pem
cz_nia/tests/key.pem
cz_nia/tests/test_functions.py
cz_nia/tests/test_message.py
cz_nia/tests/test_settings.py
cz_nia/tests/test_wsse_signature.py
cz_nia/tests/utils.py
cz_nia/tests/data/Err_response.xml
cz_nia/tests/data/FPSTS_nice.wsdl
cz_nia/tests/data/FPSTS_response.xml
cz_nia/tests/data/IPSTS_nice.wsdl
cz_nia/tests/data/IPSTS_response.xml
cz_nia/tests/data/NIA.pem
cz_nia/tests/data/Public_nice.wsdl
cz_nia/tests/data/Sub_empty_response.xml
cz_nia/tests/data/Sub_response.xml
cz_nia/tests/data/change_vip.xml
cz_nia/tests/data/change_vip_err.xml
cz_nia/tests/data/fp_token.xml
cz_nia/tests/data/notification_error.xml
cz_nia/tests/data/notifications.xml
cz_nia/tests/data/oasis-200401-wss-wssecurity-secext-1.0.xsd
cz_nia/tests/data/oasis-200401-wss-wssecurity-utility-1.0.xsd
cz_nia/tests/data/sub_token.xml
cz_nia/tests/data/test_schema.xsd
cz_nia/tests/data/write_vip.xml
cz_nia/tests/data/write_vip_err.xml
cz_nia/tests/data/ws-addr.xsd
cz_nia/tests/data/ws-policy.xsd
cz_nia/tests/data/ws-trust-1.3.xsd
cz_nia/tests/data/xml.xsd
cz_nia/tests/data/xmldsig-core-schema.xsd
cz_nia/wsse/__init__.py
cz_nia/wsse/signature.py