Metadata-Version: 2.1
Name: cz-nia
Version: 0.7
Summary: Python application for communication with Czech NIA.
Home-page: https://github.com/CZ-NIC/python-cz-nia
Author: Tomas Pazderka
Author-email: tomas.pazderka@nic.cz
License: UNKNOWN
Platform: UNKNOWN
Requires-Python: ~=3.5
Provides-Extra: quality
Provides-Extra: tests
